Workbook

Sheet Income
A1: INCOME & OFFERINGS RECORD
A2: Record all money received. Two people should count and sign for every collection - this protects the treasurer and builds trust.
A3: Date | B3: Service / Event | C3: Tithes (R) | D3: Offerings (R) | E3: Donations (R) | F3: Total (R) | G3: Counted By
F4: =IF(COUNT(C4:E4)=0,"",SUM(C4:E4))
F5: =IF(COUNT(C5:E5)=0,"",SUM(C5:E5))
F6: =IF(COUNT(C6:E6)=0,"",SUM(C6:E6))
F7: =IF(COUNT(C7:E7)=0,"",SUM(C7:E7))
F8: =IF(COUNT(C8:E8)=0,"",SUM(C8:E8))
F9: =IF(COUNT(C9:E9)=0,"",SUM(C9:E9))
F10: =IF(COUNT(C10:E10)=0,"",SUM(C10:E10))
F11: =IF(COUNT(C11:E11)=0,"",SUM(C11:E11))
F12: =IF(COUNT(C12:E12)=0,"",SUM(C12:E12))
F13: =IF(COUNT(C13:E13)=0,"",SUM(C13:E13))
F14: =IF(COUNT(C14:E14)=0,"",SUM(C14:E14))
F15: =IF(COUNT(C15:E15)=0,"",SUM(C15:E15))
... F43: =IF(COUNT(C43:E43)=0,"",SUM(C43:E43))
B44: TOTALS | C44: =SUM(C4:C43) -> 0 | D44: =SUM(D4:D43) -> 0 | E44: =SUM(E4:E43) -> 0 | F44: =SUM(F4:F43) -> 0

Sheet Expenses
A1: EXPENSES RECORD
A2: Record every payment out, with a receipt number. Every expense should be approved by someone other than the person paying it.
A3: Date | B3: What It Was For | C3: Category | D3: Amount (R) | E3: Receipt No. | F3: Approved By
A4: 2026-01-10 | B4: Example: Electricity account | C4: Utilities | E4: REC-001 | F4: Deacon Board
C44: TOTAL EXPENSES | D44: =SUM(D4:D43) -> 0
A46: Suggested categories: Utilities · Rent · Salaries · Outreach · Maintenance · Events · Transport · Equipment · Charity

Sheet Member Register
A1: MEMBER REGISTER
A2: Keep member contact details here. Under POPIA you must keep this information safe and only use it for church purposes.
A3: No. | B3: Full Name | C3: Phone | D3: Email | E3: Date Joined | F3: Ministry / Group | G3: Status
A4: 1 | B4: Example: Thandi Zulu | C4: 072 555 6666 | D4: thandi@email.com | E4: 2024-03-10 | F4: Youth | G4: Active
A5: 2
A6: 3
A7: 4
A8: 5
A9: 6
A10: 7
A11: 8
A12: 9
A13: 10
A14: 11
A15: 12
A16: 13
... A53: 50
B54: ACTIVE MEMBERS | C54: =COUNTIF(G4:G53,"Active") -> 1

Sheet Treasurers Report
A1: TREASURER'S REPORT
A2: This report fills in automatically from the Income and Expenses sheets. Print it and present it at every meeting.
A4: PERIOD
B5: Organisation Name | C5: [Your Church / NPO Name]
B6: Report Period | C6: [e.g. January 2026]
B7: Prepared By | C7: [Treasurer Name]
A9: FINANCIAL POSITION
B10: Opening Balance (enter manually) | C10: 0
B11: Total Income Received | C11: =Income!F44 -> 0
B12: Total Expenses Paid | C12: =Expenses!D44 -> 0
B13: CLOSING BALANCE | C13: =C10+C11-C12 -> 0
A15: BREAKDOWN OF INCOME
B16: Tithes | C16: =Income!C44 -> 0
B17: Offerings | C17: =Income!D44 -> 0
B18: Donations | C18: =Income!E44 -> 0
A21: SIGN-OFF
B22: Treasurer Signature
B23: Date
B24: Chairperson Signature
B25: Date
A27: Yellow cell = enter this manually. Everything else calculates from the Income and Expenses sheets.
