Workbook

Sheet Daily Sales
A1: DAILY SALES & PROFIT TRACKER
A2: Enter your takings and what you spent each day. Gross Profit and Cash Difference calculate automatically. Cash Difference should be zero - if not, money is missing.
A3: Date | B3: Cash Sales (R) | C3: Card Sales (R) | D3: Total Sales (R) | E3: Stock Bought (R) | F3: Gross Profit (R) | G3: Notes
D4: =IF(AND(B4="",C4=""),"",SUM(B4:C4)) | F4: =IF(D4="","",D4-IF(E4="",0,E4))
D5: =IF(AND(B5="",C5=""),"",SUM(B5:C5)) | F5: =IF(D5="","",D5-IF(E5="",0,E5))
D6: =IF(AND(B6="",C6=""),"",SUM(B6:C6)) | F6: =IF(D6="","",D6-IF(E6="",0,E6))
D7: =IF(AND(B7="",C7=""),"",SUM(B7:C7)) | F7: =IF(D7="","",D7-IF(E7="",0,E7))
D8: =IF(AND(B8="",C8=""),"",SUM(B8:C8)) | F8: =IF(D8="","",D8-IF(E8="",0,E8))
D9: =IF(AND(B9="",C9=""),"",SUM(B9:C9)) | F9: =IF(D9="","",D9-IF(E9="",0,E9))
D10: =IF(AND(B10="",C10=""),"",SUM(B10:C10)) | F10: =IF(D10="","",D10-IF(E10="",0,E10))
D11: =IF(AND(B11="",C11=""),"",SUM(B11:C11)) | F11: =IF(D11="","",D11-IF(E11="",0,E11))
D12: =IF(AND(B12="",C12=""),"",SUM(B12:C12)) | F12: =IF(D12="","",D12-IF(E12="",0,E12))
D13: =IF(AND(B13="",C13=""),"",SUM(B13:C13)) | F13: =IF(D13="","",D13-IF(E13="",0,E13))
D14: =IF(AND(B14="",C14=""),"",SUM(B14:C14)) | F14: =IF(D14="","",D14-IF(E14="",0,E14))
D15: =IF(AND(B15="",C15=""),"",SUM(B15:C15)) | F15: =IF(D15="","",D15-IF(E15="",0,E15))
... D34: =IF(AND(B34="",C34=""),"",SUM(B34:C34)) | F34: =IF(D34="","",D34-IF(E34="",0,E34))
A35: MONTH TOTALS | B35: =SUM(B4:B34) -> 0 | C35: =SUM(C4:C34) -> 0 | D35: =SUM(D4:D34) -> 0 | E35: =SUM(E4:E34) -> 0 | F35: =SUM(F4:F34) -> 0

Sheet Stock & Reorder
A1: STOCK LEVELS & REORDER ALERTS
A2: Set a Reorder Level for each item. The Status column tells you when to buy more - watch for REORDER NOW.
A3: No. | B3: Product | C3: In Stock | D3: Reorder Level | E3: Cost (R) | F3: Sell (R) | G3: Profit per Item | H3: Status
A4: 1 | B4: Example: 2L Coke | C4: 12 | D4: 6
A5: 2 | G5: =IF(AND(E5<>"",F5<>""),F5-E5,"") | H5: =IF(B5="","",IF(C5="","",IF(C5<=0,"OUT OF STOCK",IF(AND(D5<>"",C5<=D5),"REORDER NOW","OK"))))
A6: 3 | G6: =IF(AND(E6<>"",F6<>""),F6-E6,"") | H6: =IF(B6="","",IF(C6="","",IF(C6<=0,"OUT OF STOCK",IF(AND(D6<>"",C6<=D6),"REORDER NOW","OK"))))
A7: 4 | G7: =IF(AND(E7<>"",F7<>""),F7-E7,"") | H7: =IF(B7="","",IF(C7="","",IF(C7<=0,"OUT OF STOCK",IF(AND(D7<>"",C7<=D7),"REORDER NOW","OK"))))
A8: 5 | G8: =IF(AND(E8<>"",F8<>""),F8-E8,"") | H8: =IF(B8="","",IF(C8="","",IF(C8<=0,"OUT OF STOCK",IF(AND(D8<>"",C8<=D8),"REORDER NOW","OK"))))
A9: 6 | G9: =IF(AND(E9<>"",F9<>""),F9-E9,"") | H9: =IF(B9="","",IF(C9="","",IF(C9<=0,"OUT OF STOCK",IF(AND(D9<>"",C9<=D9),"REORDER NOW","OK"))))
A10: 7 | G10: =IF(AND(E10<>"",F10<>""),F10-E10,"") | H10: =IF(B10="","",IF(C10="","",IF(C10<=0,"OUT OF STOCK",IF(AND(D10<>"",C10<=D10),"REORDER NOW","OK"))))
A11: 8 | G11: =IF(AND(E11<>"",F11<>""),F11-E11,"") | H11: =IF(B11="","",IF(C11="","",IF(C11<=0,"OUT OF STOCK",IF(AND(D11<>"",C11<=D11),"REORDER NOW","OK"))))
A12: 9 | G12: =IF(AND(E12<>"",F12<>""),F12-E12,"") | H12: =IF(B12="","",IF(C12="","",IF(C12<=0,"OUT OF STOCK",IF(AND(D12<>"",C12<=D12),"REORDER NOW","OK"))))
A13: 10 | G13: =IF(AND(E13<>"",F13<>""),F13-E13,"") | H13: =IF(B13="","",IF(C13="","",IF(C13<=0,"OUT OF STOCK",IF(AND(D13<>"",C13<=D13),"REORDER NOW","OK"))))
A14: 11 | G14: =IF(AND(E14<>"",F14<>""),F14-E14,"") | H14: =IF(B14="","",IF(C14="","",IF(C14<=0,"OUT OF STOCK",IF(AND(D14<>"",C14<=D14),"REORDER NOW","OK"))))
A15: 12 | G15: =IF(AND(E15<>"",F15<>""),F15-E15,"") | H15: =IF(B15="","",IF(C15="","",IF(C15<=0,"OUT OF STOCK",IF(AND(D15<>"",C15<=D15),"REORDER NOW","OK"))))
A16: 13 | G16: =IF(AND(E16<>"",F16<>""),F16-E16,"") | H16: =IF(B16="","",IF(C16="","",IF(C16<=0,"OUT OF STOCK",IF(AND(D16<>"",C16<=D16),"REORDER NOW","OK"))))
... A43: 40 | G43: =IF(AND(E43<>"",F43<>""),F43-E43,"") | H43: =IF(B43="","",IF(C43="","",IF(C43<=0,"OUT OF STOCK",IF(AND(D43<>"",C43<=D43),"REORDER NOW","OK"))))
B44: STOCK VALUE AT COST | E44: =SUMPRODUCT(C4:C43,N(E4:E43)) -> 0

Sheet Suppliers
A1: SUPPLIER CONTACT LIST
A2: Keep every supplier here so you can reorder fast. Note their delivery days so you plan your buying.
A3: No. | B3: Supplier Name | C3: Contact Person | D3: Phone | E3: What They Supply | F3: Delivery Days
A4: 1 | B4: Example: Cash & Carry CT | C4: Mr Patel | D4: 021 123 4567 | E4: Cold drinks, chips, bread | F4: Mon & Thu
A5: 2
A6: 3
A7: 4
A8: 5
A9: 6
A10: 7
A11: 8
A12: 9
A13: 10
A14: 11
A15: 12
A16: 13
... A23: 20

Sheet Monthly Summary
A1: MONTHLY BUSINESS SUMMARY
A3: THIS MONTH
B4: Total Sales | C4: ='Daily Sales'!D35 -> 0
B5: Total Spent on Stock | C5: ='Daily Sales'!E35 -> 0
B6: GROSS PROFIT | C6: ='Daily Sales'!F35 -> 0
B8: Items Needing Reorder | C8: =COUNTIF('Stock & Reorder'!H4:H43,"REORDER NOW") -> 0
B9: Items Out of Stock | C9: =COUNTIF('Stock & Reorder'!H4:H43,"OUT OF STOCK") -> 0
B10: Current Stock Value (at cost) | C10: ='Stock & Reorder'!E44 -> 0
A13: Gross profit is sales minus stock bought. Remember to also subtract rent, electricity and transport to know your real profit.
