Workbook

Sheet Trip Log
A1: DAILY TRIP LOG
A2: Record every trip. Distance and Net Earnings calculate automatically. Keep this for SARS - trip records are what prove your vehicle expenses.
A3: Date | B3: Driver | C3: From | D3: To | E3: Odo Start | F3: Odo End | G3: Distance (km) | H3: Fare Earned (R) | I3: Net after Fuel (R) | K3: SETTING
G4: =IF(AND(E4<>"",F4<>""),F4-E4,"") | I4: =IF(H4="","",H4-IF(G4="",0,G4*$L$4)) | K4: Fuel cost per km (R) | L4: 2.5
G5: =IF(AND(E5<>"",F5<>""),F5-E5,"") | I5: =IF(H5="","",H5-IF(G5="",0,G5*$L$4)) | K5: EDIT THIS to match your vehicle
G6: =IF(AND(E6<>"",F6<>""),F6-E6,"") | I6: =IF(H6="","",H6-IF(G6="",0,G6*$L$4))
G7: =IF(AND(E7<>"",F7<>""),F7-E7,"") | I7: =IF(H7="","",H7-IF(G7="",0,G7*$L$4))
G8: =IF(AND(E8<>"",F8<>""),F8-E8,"") | I8: =IF(H8="","",H8-IF(G8="",0,G8*$L$4))
G9: =IF(AND(E9<>"",F9<>""),F9-E9,"") | I9: =IF(H9="","",H9-IF(G9="",0,G9*$L$4))
G10: =IF(AND(E10<>"",F10<>""),F10-E10,"") | I10: =IF(H10="","",H10-IF(G10="",0,G10*$L$4))
G11: =IF(AND(E11<>"",F11<>""),F11-E11,"") | I11: =IF(H11="","",H11-IF(G11="",0,G11*$L$4))
G12: =IF(AND(E12<>"",F12<>""),F12-E12,"") | I12: =IF(H12="","",H12-IF(G12="",0,G12*$L$4))
G13: =IF(AND(E13<>"",F13<>""),F13-E13,"") | I13: =IF(H13="","",H13-IF(G13="",0,G13*$L$4))
G14: =IF(AND(E14<>"",F14<>""),F14-E14,"") | I14: =IF(H14="","",H14-IF(G14="",0,G14*$L$4))
G15: =IF(AND(E15<>"",F15<>""),F15-E15,"") | I15: =IF(H15="","",H15-IF(G15="",0,G15*$L$4))
G16: =IF(AND(E16<>"",F16<>""),F16-E16,"") | I16: =IF(H16="","",H16-IF(G16="",0,G16*$L$4))
G17: =IF(AND(E17<>"",F17<>""),F17-E17,"") | I17: =IF(H17="","",H17-IF(G17="",0,G17*$L$4))
... G43: =IF(AND(E43<>"",F43<>""),F43-E43,"") | I43: =IF(H43="","",H43-IF(G43="",0,G43*$L$4))
D44: TOTALS | G44: =SUM(G4:G43) -> 0 | H44: =SUM(H4:H43) -> 0 | I44: =SUM(I4:I43) -> 0

Sheet Fuel Log
A1: FUEL & CONSUMPTION LOG
A2: Fill in every fill-up. Litres per 100km shows if your vehicle is using too much fuel - a sudden jump usually means a mechanical problem.
A3: Date | B3: Station | C3: Litres | D3: Price/Litre (R) | E3: Total Paid (R) | F3: Odometer | G3: Km Travelled | H3: Litres per 100km
E4: =IF(AND(C4<>"",D4<>""),C4*D4,"")
E5: =IF(AND(C5<>"",D5<>""),C5*D5,"") | G5: =IF(AND(F5<>"",F4<>""),F5-F4,"") | H5: =IF(AND(G5<>"",G5>0,C5<>""),C5/G5*100,"")
E6: =IF(AND(C6<>"",D6<>""),C6*D6,"") | G6: =IF(AND(F6<>"",F5<>""),F6-F5,"") | H6: =IF(AND(G6<>"",G6>0,C6<>""),C6/G6*100,"")
E7: =IF(AND(C7<>"",D7<>""),C7*D7,"") | G7: =IF(AND(F7<>"",F6<>""),F7-F6,"") | H7: =IF(AND(G7<>"",G7>0,C7<>""),C7/G7*100,"")
E8: =IF(AND(C8<>"",D8<>""),C8*D8,"") | G8: =IF(AND(F8<>"",F7<>""),F8-F7,"") | H8: =IF(AND(G8<>"",G8>0,C8<>""),C8/G8*100,"")
E9: =IF(AND(C9<>"",D9<>""),C9*D9,"") | G9: =IF(AND(F9<>"",F8<>""),F9-F8,"") | H9: =IF(AND(G9<>"",G9>0,C9<>""),C9/G9*100,"")
E10: =IF(AND(C10<>"",D10<>""),C10*D10,"") | G10: =IF(AND(F10<>"",F9<>""),F10-F9,"") | H10: =IF(AND(G10<>"",G10>0,C10<>""),C10/G10*100,"")
E11: =IF(AND(C11<>"",D11<>""),C11*D11,"") | G11: =IF(AND(F11<>"",F10<>""),F11-F10,"") | H11: =IF(AND(G11<>"",G11>0,C11<>""),C11/G11*100,"")
E12: =IF(AND(C12<>"",D12<>""),C12*D12,"") | G12: =IF(AND(F12<>"",F11<>""),F12-F11,"") | H12: =IF(AND(G12<>"",G12>0,C12<>""),C12/G12*100,"")
E13: =IF(AND(C13<>"",D13<>""),C13*D13,"") | G13: =IF(AND(F13<>"",F12<>""),F13-F12,"") | H13: =IF(AND(G13<>"",G13>0,C13<>""),C13/G13*100,"")
E14: =IF(AND(C14<>"",D14<>""),C14*D14,"") | G14: =IF(AND(F14<>"",F13<>""),F14-F13,"") | H14: =IF(AND(G14<>"",G14>0,C14<>""),C14/G14*100,"")
E15: =IF(AND(C15<>"",D15<>""),C15*D15,"") | G15: =IF(AND(F15<>"",F14<>""),F15-F14,"") | H15: =IF(AND(G15<>"",G15>0,C15<>""),C15/G15*100,"")
E16: =IF(AND(C16<>"",D16<>""),C16*D16,"") | G16: =IF(AND(F16<>"",F15<>""),F16-F15,"") | H16: =IF(AND(G16<>"",G16>0,C16<>""),C16/G16*100,"")
... E43: =IF(AND(C43<>"",D43<>""),C43*D43,"") | G43: =IF(AND(F43<>"",F42<>""),F43-F42,"") | H43: =IF(AND(G43<>"",G43>0,C43<>""),C43/G43*100,"")
B44: TOTALS | C44: =SUM(C4:C43) -> 0 | E44: =SUM(E4:E43) -> 0 | G44: =SUM(G4:G43) -> 0

Sheet Maintenance
A1: SERVICE & MAINTENANCE RECORD
A2: Track every service and repair. Next Service Due helps you avoid breakdowns - a broken vehicle earns nothing.
A3: Date | B3: Work Done | C3: Odometer | D3: Cost (R) | E3: Workshop / Mechanic | F3: Next Service Due (km)
A4: 2026-01-15 | B4: Example: Oil & filter service | C4: 120000 | E4: Main Rd Motors | F4: 135000
C34: TOTAL SPENT ON MAINTENANCE | D34: =SUM(D4:D33) -> 0

Sheet Driver Schedule
A1: DRIVER SCHEDULE & PAY
A2: Track shifts and what each driver is owed. Pay Due calculates from hours worked. Check PRDP licence expiry dates - driving without one is illegal.
A3: No. | B3: Driver Name | C3: Phone | D3: Shift | E3: Hours Worked | F3: Rate/Hour (R) | G3: Pay Due (R)
A4: 1 | B4: Example: T. Mbeki | C4: 072 333 4444 | D4: Day
A5: 2 | G5: =IF(AND(E5<>"",F5<>""),E5*F5,"")
A6: 3 | G6: =IF(AND(E6<>"",F6<>""),E6*F6,"")
A7: 4 | G7: =IF(AND(E7<>"",F7<>""),E7*F7,"")
A8: 5 | G8: =IF(AND(E8<>"",F8<>""),E8*F8,"")
A9: 6 | G9: =IF(AND(E9<>"",F9<>""),E9*F9,"")
A10: 7 | G10: =IF(AND(E10<>"",F10<>""),E10*F10,"")
A11: 8 | G11: =IF(AND(E11<>"",F11<>""),E11*F11,"")
A12: 9 | G12: =IF(AND(E12<>"",F12<>""),E12*F12,"")
A13: 10 | G13: =IF(AND(E13<>"",F13<>""),E13*F13,"")
A14: 11 | G14: =IF(AND(E14<>"",F14<>""),E14*F14,"")
A15: 12 | G15: =IF(AND(E15<>"",F15<>""),E15*F15,"")
A16: 13 | G16: =IF(AND(E16<>"",F16<>""),E16*F16,"")
... A28: 25 | G28: =IF(AND(E28<>"",F28<>""),E28*F28,"")
E29: TOTAL WAGES DUE | G29: =SUM(G4:G28) -> 0

Sheet Summary
A1: BUSINESS SUMMARY
A3: EARNINGS & COSTS
B4: Total Fares Earned | C4: ='Trip Log'!H44 -> 0
B5: Total Fuel Paid | C5: ='Fuel Log'!E44 -> 0
B6: Total Maintenance | C6: =Maintenance!D34 -> 0
B7: Total Driver Wages | C7: ='Driver Schedule'!G29 -> 0
B8: NET PROFIT | C8: =C4-C5-C6-C7 -> 0
B10: Total Distance (km) | C10: ='Trip Log'!G44 -> 0
B11: Profit per km (R) | C11: =IF(C10=0,"",C8/C10)
A13: Net profit is fares minus fuel, maintenance and wages. Remember to also budget for insurance, licence renewals and vehicle finance.
